MANIFEST.in
README.md
requirements.txt
setup.cfg
setup.py
versioneer.py
botcity/plugins/aws/s3/__init__.py
botcity/plugins/aws/s3/_version.py
botcity/plugins/aws/s3/filter.py
botcity/plugins/aws/s3/plugin.py
botcity/plugins/aws/s3/utils.py
botcity_aws_s3_plugin.egg-info/PKG-INFO
botcity_aws_s3_plugin.egg-info/SOURCES.txt
botcity_aws_s3_plugin.egg-info/dependency_links.txt
botcity_aws_s3_plugin.egg-info/requires.txt
botcity_aws_s3_plugin.egg-info/top_level.txt