Metadata-Version: 2.1
Name: botcity-aws-s3-plugin
Version: 0.1.2
Home-page: https://bitbucket.org/botcitydev/bot-aws-s3-plugin-python.git
Requires-Python: >=3.7
